Workbook

Sheet NPV
D2: Year 0 | E2: Year 1 | F2: Year 2 | G2: Year 3 | H2: Year 4 | I2: Year 5 | J2: Year 6 | K2: Year 7 | L2: Year 8 | M2: Year 9 | N2: Year 10
C3: Cash Inflow (Good) | D3: 0 | E3: 1400000 | F3: 1400000 | G3: 1400000 | H3: 1400000 | I3: 1400000 | J3: 1400000 | K3: 1400000 | L3: 1400000 | M3: 1400000 | N3: 1400000
C4: Cash Inflow (Medium) | D4: 0 | E4: =E3*0.75 -> 1050000 | F4: =F3*0.75 -> 1050000 | G4: =G3*0.75 -> 1050000 | H4: =H3*0.75 -> 1050000 | I4: =I3*0.75 -> 1050000 | J4: =J3*0.75 -> 1050000 | K4: =K3*0.75 -> 1050000 | L4: =L3*0.75 -> 1050000 | ... N4: =N3*0.75 -> 1050000
C5: Cash Inflow (Bad) | D5: 0 | E5: =E3*0.5 -> 700000 | F5: =F3*0.5 -> 700000 | G5: =G3*0.5 -> 700000 | H5: =H3*0.5 -> 700000 | I5: =I3*0.5 -> 700000 | J5: =J3*0.5 -> 700000 | K5: =K3*0.5 -> 700000 | L5: =L3*0.5 -> 700000 | ... N5: =N3*0.5 -> 700000
C6: Cash Outflow | D6: -342534 | E6: -525207 | F6: -525207 | G6: -525207 | H6: -525207 | I6: -525207 | J6: -525207 | K6: -525207 | L6: -525207 | M6: -525207 | N6: -525207
C7: Net Cash Flow (p) (Good) | D7: =SUM(D3,D6) -> -342534 | E7: =SUM(E3,E6) -> 874793 | F7: =SUM(F3,F6) -> 874793 | G7: =SUM(G3,G6) -> 874793 | H7: =SUM(H3,H6) -> 874793 | I7: =SUM(I3,I6) -> 874793 | J7: =SUM(J3,J6) -> 874793 | K7: =SUM(K3,K6) -> 874793 | ... N7: =SUM(N3,N6) -> 874793
C8: Net Cash Flow(p) Medium) | D8: =SUM(D4,D6) -> -342534 | E8: =SUM(E4,E6) -> 524793 | F8: =SUM(F4,F6) -> 524793 | G8: =SUM(G4,G6) -> 524793 | H8: =SUM(H4,H6) -> 524793 | I8: =SUM(I4,I6) -> 524793 | J8: =SUM(J4,J6) -> 524793 | K8: =SUM(K4,K6) -> 524793 | ... N8: =SUM(N4,N6) -> 524793
C9: Net Cash Flow (p) (Bad) | D9: =SUM(D5,D6) -> -342534 | E9: =SUM(E5,E6) -> 174793 | F9: =SUM(F5,F6) -> 174793 | G9: =SUM(G5,G6) -> 174793 | H9: =SUM(H5,H6) -> 174793 | I9: =SUM(I5,I6) -> 174793 | J9: =SUM(J5,J6) -> 174793 | K9: =SUM(K5,K6) -> 174793 | ... N9: =SUM(N5,N6) -> 174793
B10: Scenario 1: | C10: PV (i=%30) (p=good) | D10: =D7 -> -342534 | E10: =E7/(1+0.3) -> 672917.69 | F10: =F7/((1+0.3)*(1+0.3)) -> 517628.99 | G10: =G7/((1+0.3)*(1+0.3)*(1+0.3)) -> 398176.15 | H10: =H7/((1+0.3)*(1+0.3)*(1+0.3)*(1+0.3)) -> 306289.35 | I10: =I7/((1+0.3)*(1+0.3)*(1+0.3)*(1+0.3)*(1+0.3)) -> 235607.19 | J10: =J7/((1+0.3)*(1+0.3)*(1+0.3)*(1+0.3)*(1+0.3)*(1+0.3)) -> 181236.3 | K10: =K7/((1+0.3)*(1+0.3)*(1+0.3)*(1+0.3)*(1+0.3)*(1+0.3)*(1+0.3)) -> 139412.54 | L10: =L7/((1+0.3)*(1+0.3)*(1+0.3)*(1+0.3)*(1+0.3)*(1+0.3)*(1+0.3)*(1+0.3)) -> 107240.41 | M10: =M7/((1+0.3)*(1+0.3)*(1+0.3)*(1+0.3)*(1+0.3)*(1+0.3)*(1+0.3)*(1+0.3)*(1+0.3)) -> 82492.626 | N10: =N7/((1+0.3)*(1+0.3)*(1+0.3)*(1+0.3)*(1+0.3)*(1+0.3)*(1+0.3)*(1+0.3)*(1+0.3)*(1+0.3)) -> 63455.866
B11: Scenario 2: | C11: PV (i=%30) (p=medium) | D11: =D8 -> -342534 | E11: =E8/(1+0.3) -> 403686.92 | F11: =F8/((1+0.3)*(1+0.3)) -> 310528.4 | G11: =G8/((1+0.3)*(1+0.3)*(1+0.3)) -> 238868 | H11: =H8/((1+0.3)*(1+0.3)*(1+0.3)*(1+0.3)) -> 183744.62 | I11: =I8/((1+0.3)*(1+0.3)*(1+0.3)*(1+0.3)*(1+0.3)) -> 141342.01 | J11: =J8/((1+0.3)*(1+0.3)*(1+0.3)*(1+0.3)*(1+0.3)*(1+0.3)) -> 108724.63 | K11: =K8/((1+0.3)*(1+0.3)*(1+0.3)*(1+0.3)*(1+0.3)*(1+0.3)*(1+0.3)) -> 83634.327 | L11: =L8/((1+0.3)*(1+0.3)*(1+0.3)*(1+0.3)*(1+0.3)*(1+0.3)*(1+0.3)*(1+0.3)) -> 64334.098 | M11: =M8/((1+0.3)*(1+0.3)*(1+0.3)*(1+0.3)*(1+0.3)*(1+0.3)*(1+0.3)*(1+0.3)*(1+0.3)) -> 49487.768 | N11: =N8/((1+0.3)*(1+0.3)*(1+0.3)*(1+0.3)*(1+0.3)*(1+0.3)*(1+0.3)*(1+0.3)*(1+0.3)*(1+0.3)) -> 38067.514
B12: Scenario 3: | C12: PV (i=%30) (p=bad) | D12: =D9 -> -342534 | E12: =E9/(1+0.3) -> 134456.15 | F12: =F9/((1+0.3)*(1+0.3)) -> 103427.81 | G12: =G9/((1+0.3)*(1+0.3)*(1+0.3)) -> 79559.854 | H12: =H9/((1+0.3)*(1+0.3)*(1+0.3)*(1+0.3)) -> 61199.888 | I12: =I9/((1+0.3)*(1+0.3)*(1+0.3)*(1+0.3)*(1+0.3)) -> 47076.837 | J12: =J9/((1+0.3)*(1+0.3)*(1+0.3)*(1+0.3)*(1+0.3)*(1+0.3)) -> 36212.951 | K12: =K9/((1+0.3)*(1+0.3)*(1+0.3)*(1+0.3)*(1+0.3)*(1+0.3)*(1+0.3)) -> 27856.117 | L12: =L9/((1+0.3)*(1+0.3)*(1+0.3)*(1+0.3)*(1+0.3)*(1+0.3)*(1+0.3)*(1+0.3)) -> 21427.782 | M12: =M9/((1+0.3)*(1+0.3)*(1+0.3)*(1+0.3)*(1+0.3)*(1+0.3)*(1+0.3)*(1+0.3)*(1+0.3)) -> 16482.909 | N12: =N9/((1+0.3)*(1+0.3)*(1+0.3)*(1+0.3)*(1+0.3)*(1+0.3)*(1+0.3)*(1+0.3)*(1+0.3)*(1+0.3)) -> 12679.161
B13: Scenario 4: | C13: PV (i=%40) (p=good) | D13: =D7 -> -342534 | E13: =E7/(1+0.4) -> 624852.14 | F13: =F7/((1+0.4)*(1+0.4)) -> 446322.96 | G13: =G7/((1+0.4)*(1+0.4)*(1+0.4)) -> 318802.11 | H13: =H7/((1+0.4)*(1+0.4)*(1+0.4)*(1+0.4)) -> 227715.8 | I13: =I7/((1+0.4)*(1+0.4)*(1+0.4)*(1+0.4)*(1+0.4)) -> 162654.14 | J13: =J7/((1+0.4)*(1+0.4)*(1+0.4)*(1+0.4)*(1+0.4)*(1+0.4)) -> 116181.53 | K13: =K7/((1+0.4)*(1+0.4)*(1+0.4)*(1+0.4)*(1+0.4)*(1+0.4)*(1+0.4)) -> 82986.806 | L13: =L7/((1+0.4)*(1+0.4)*(1+0.4)*(1+0.4)*(1+0.4)*(1+0.4)*(1+0.4)*(1+0.4)) -> 59276.29 | M13: =M7/((1+0.4)*(1+0.4)*(1+0.4)*(1+0.4)*(1+0.4)*(1+0.4)*(1+0.4)*(1+0.4)*(1+0.4)) -> 42340.207 | N13: =N7/((1+0.4)*(1+0.4)*(1+0.4)*(1+0.4)*(1+0.4)*(1+0.4)*(1+0.4)*(1+0.4)*(1+0.4)*(1+0.4)) -> 30243.005
B14: Scenario 5: | C14: PV (i=%40) (p=medium) | D14: =D8 -> -342534 | E14: =E8/(1+0.4) -> 374852.14 | F14: =F8/((1+0.4)*(1+0.4)) -> 267751.53 | G14: =G8/((1+0.4)*(1+0.4)*(1+0.4)) -> 191251.09 | H14: =H8/((1+0.4)*(1+0.4)*(1+0.4)*(1+0.4)) -> 136607.92 | I14: =I8/((1+0.4)*(1+0.4)*(1+0.4)*(1+0.4)*(1+0.4)) -> 97577.088 | J14: =J8/((1+0.4)*(1+0.4)*(1+0.4)*(1+0.4)*(1+0.4)*(1+0.4)) -> 69697.92 | K14: =K8/((1+0.4)*(1+0.4)*(1+0.4)*(1+0.4)*(1+0.4)*(1+0.4)*(1+0.4)) -> 49784.229 | L14: =L8/((1+0.4)*(1+0.4)*(1+0.4)*(1+0.4)*(1+0.4)*(1+0.4)*(1+0.4)*(1+0.4)) -> 35560.163 | M14: =M8/((1+0.4)*(1+0.4)*(1+0.4)*(1+0.4)*(1+0.4)*(1+0.4)*(1+0.4)*(1+0.4)*(1+0.4)) -> 25400.117 | N14: =N8/((1+0.4)*(1+0.4)*(1+0.4)*(1+0.4)*(1+0.4)*(1+0.4)*(1+0.4)*(1+0.4)*(1+0.4)*(1+0.4)) -> 18142.941
B15: Scenario 6: | C15: PV (i=%40) (p=bad) | D15: =D9 -> -342534 | E15: =E9/(1+0.4) -> 124852.14 | F15: =F9/((1+0.4)*(1+0.4)) -> 89180.102 | G15: =G9/((1+0.4)*(1+0.4)*(1+0.4)) -> 63700.073 | H15: =H9/((1+0.4)*(1+0.4)*(1+0.4)*(1+0.4)) -> 45500.052 | I15: =I9/((1+0.4)*(1+0.4)*(1+0.4)*(1+0.4)*(1+0.4)) -> 32500.037 | J15: =J9/((1+0.4)*(1+0.4)*(1+0.4)*(1+0.4)*(1+0.4)*(1+0.4)) -> 23214.312 | K15: =K9/((1+0.4)*(1+0.4)*(1+0.4)*(1+0.4)*(1+0.4)*(1+0.4)*(1+0.4)) -> 16581.652 | L15: =L9/((1+0.4)*(1+0.4)*(1+0.4)*(1+0.4)*(1+0.4)*(1+0.4)*(1+0.4)*(1+0.4)) -> 11844.037 | M15: =M9/((1+0.4)*(1+0.4)*(1+0.4)*(1+0.4)*(1+0.4)*(1+0.4)*(1+0.4)*(1+0.4)*(1+0.4)) -> 8460.0263 | N15: =N9/((1+0.4)*(1+0.4)*(1+0.4)*(1+0.4)*(1+0.4)*(1+0.4)*(1+0.4)*(1+0.4)*(1+0.4)*(1+0.4)) -> 6042.876
B16: Scenario 7: | C16: PV (i=%50) (p=good) | D16: =D7 -> -342534 | E16: =E7/(1+0.5) -> 583195.33 | F16: =F7/((1+0.5)*(1+0.5)) -> 388796.89 | G16: =G7/((1+0.5)*(1+0.5)*(1+0.5)) -> 259197.93 | H16: =H7/((1+0.5)*(1+0.5)*(1+0.5)*(1+0.5)) -> 172798.62 | I16: =I7/((1+0.5)*(1+0.5)*(1+0.5)*(1+0.5)*(1+0.5)) -> 115199.08 | J16: =J7/((1+0.5)*(1+0.5)*(1+0.5)*(1+0.5)*(1+0.5)*(1+0.5)) -> 76799.385 | K16: =K7/((1+0.5)*(1+0.5)*(1+0.5)*(1+0.5)*(1+0.5)*(1+0.5)*(1+0.5)) -> 51199.59 | L16: =L7/((1+0.5)*(1+0.5)*(1+0.5)*(1+0.5)*(1+0.5)*(1+0.5)*(1+0.5)*(1+0.5)) -> 34133.06 | M16: =M7/((1+0.5)*(1+0.5)*(1+0.5)*(1+0.5)*(1+0.5)*(1+0.5)*(1+0.5)*(1+0.5)*(1+0.5)) -> 22755.373 | N16: =N7/((1+0.5)*(1+0.5)*(1+0.5)*(1+0.5)*(1+0.5)*(1+0.5)*(1+0.5)*(1+0.5)*(1+0.5)*(1+0.5)) -> 15170.249
B17: Scenario 8: | C17: PV (i=%50) (p=medium) | D17: =D8 -> -342534 | E17: =E8/(1+0.5) -> 349862 | F17: =F8/((1+0.5)*(1+0.5)) -> 233241.33 | G17: =G8/((1+0.5)*(1+0.5)*(1+0.5)) -> 155494.22 | H17: =H8/((1+0.5)*(1+0.5)*(1+0.5)*(1+0.5)) -> 103662.81 | I17: =I8/((1+0.5)*(1+0.5)*(1+0.5)*(1+0.5)*(1+0.5)) -> 69108.543 | J17: =J8/((1+0.5)*(1+0.5)*(1+0.5)*(1+0.5)*(1+0.5)*(1+0.5)) -> 46072.362 | K17: =K8/((1+0.5)*(1+0.5)*(1+0.5)*(1+0.5)*(1+0.5)*(1+0.5)*(1+0.5)) -> 30714.908 | L17: =L8/((1+0.5)*(1+0.5)*(1+0.5)*(1+0.5)*(1+0.5)*(1+0.5)*(1+0.5)*(1+0.5)) -> 20476.605 | M17: =M8/((1+0.5)*(1+0.5)*(1+0.5)*(1+0.5)*(1+0.5)*(1+0.5)*(1+0.5)*(1+0.5)*(1+0.5)) -> 13651.07 | N17: =N8/((1+0.5)*(1+0.5)*(1+0.5)*(1+0.5)*(1+0.5)*(1+0.5)*(1+0.5)*(1+0.5)*(1+0.5)*(1+0.5)) -> 9100.7135
B18: Scenario 9: | C18: PV (i=%50) (p=bad) | D18: =D9 -> -342534 | E18: =E9/(1+0.5) -> 116528.67 | F18: =F9/((1+0.5)*(1+0.5)) -> 77685.778 | G18: =G9/((1+0.5)*(1+0.5)*(1+0.5)) -> 51790.519 | H18: =H9/((1+0.5)*(1+0.5)*(1+0.5)*(1+0.5)) -> 34527.012 | I18: =I9/((1+0.5)*(1+0.5)*(1+0.5)*(1+0.5)*(1+0.5)) -> 23018.008 | J18: =J9/((1+0.5)*(1+0.5)*(1+0.5)*(1+0.5)*(1+0.5)*(1+0.5)) -> 15345.339 | K18: =K9/((1+0.5)*(1+0.5)*(1+0.5)*(1+0.5)*(1+0.5)*(1+0.5)*(1+0.5)) -> 10230.226 | L18: =L9/((1+0.5)*(1+0.5)*(1+0.5)*(1+0.5)*(1+0.5)*(1+0.5)*(1+0.5)*(1+0.5)) -> 6820.1506 | M18: =M9/((1+0.5)*(1+0.5)*(1+0.5)*(1+0.5)*(1+0.5)*(1+0.5)*(1+0.5)*(1+0.5)*(1+0.5)) -> 4546.7671 | N18: =N9/((1+0.5)*(1+0.5)*(1+0.5)*(1+0.5)*(1+0.5)*(1+0.5)*(1+0.5)*(1+0.5)*(1+0.5)*(1+0.5)) -> 3031.178
E21: NPV | F21: Probability | G21: Expected NPV | J21: IRR | K21: ROI | L21: Payback Period
D22: Scenario 1: | E22: =SUM(D10:N10) -> 2361923.1 | F22: 0.09 | G22: =E22*F22+E23*F23+E24*F24+E25*F25+E26*F26+E27*F27+E28*F28+E29*F29+E30*F30 -> 955752.68
D23: Scenario 2: | E23: =SUM(D11:N11) -> 1279884.3 | F23: 0.11
D24: Scenario 3: | E24: =SUM(D12:N12) -> 197845.46 | F24: 0.11
D25: Scenario 4: | E25: =SUM(D13:N13) -> 1768841 | F25: 0.1
D26: Scenario 5: | E26: =SUM(D14:N14) -> 924091.15 | F26: 0.16
D27: Scenario 6: | E27: =SUM(D15:N15) -> 79341.31 | F27: 0.1
D28: Scenario 7: | E28: =SUM(D16:N16) -> 1376711.5 | F28: 0.12
D29: Scenario 8: | E29: =SUM(D17:N17) -> 688850.57 | F29: 0.12
D30: Scenario 9: | E30: =SUM(D18:N18) -> 989.64392 | F30: 0.09

Sheet Financial Analysis
B2: Year | C2: Cash Flow (Best) (100%) | D2: Cash Flow (Base) (83%) | E2: Cash Flow (Worst) (66%) | F2: Discount Rate Factor (Best) (i = 39,50) | G2: Discount Rate Factor (Base) (i = 44,08) | H2: Discount Rate Factor (Worst) (i = 49,00) | J2: Discount Rate (Best) | K2: Discount Rate (Base) | L2: Discount Rate (Worst)
B3: 0 | C3: =-'Capacity Using Rate & Cash Flow'!C4 -> -342534.5 | D3: =C3 -> -342534.5 | E3: =C3 -> -342534.5 | F3: =1/(1+$J$3)^B3 -> 1 | G3: =1/(1+$K$3)^B3 -> 1 | H3: =1/(1+$L$3)^B3 -> 1 | J3: ='Discount Rate'!$F$6 -> 0.395 | K3: ='Discount Rate'!$G$6 -> 0.4408 | L3: ='Discount Rate'!$H$6 -> 0.49
B4: 1 | C4: ='Capacity Using Rate & Cash Flow'!C8 -> 816522.52 | D4: ='Capacity Using Rate & Cash Flow'!D8 -> 677713.69 | E4: ='Capacity Using Rate & Cash Flow'!E8 -> 538904.86 | F4: =1/(1+$J$3)^B4 -> 0.71684588 | G4: =1/(1+$K$3)^B4 -> 0.69405886 | H4: =1/(1+$L$3)^B4 -> 0.67114094 | J4: ='Discount Rate'!$F$6 -> 0.395 | K4: ='Discount Rate'!$G$6 -> 0.4408 | L4: ='Discount Rate'!$H$6 -> 0.49
B5: 2 | C5: =C4*(1.44) -> 1175792.4 | D5: =D4*(1.44) -> 975907.72 | E5: =E4*1.44 -> 776023 | F5: =1/(1+$J$3)^B5 -> 0.51386801 | G5: =1/(1+$K$3)^B5 -> 0.4817177 | H5: =1/(1+$L$3)^B5 -> 0.45043016 | J5: ='Discount Rate'!$F$6 -> 0.395 | K5: ='Discount Rate'!$G$6 -> 0.4408 | L5: ='Discount Rate'!$H$6 -> 0.49
B6: 3 | C6: =C5*(1.44) -> 1693141.1 | D6: =D5*(1.44) -> 1405307.1 | E6: =E5*1.44 -> 1117473.1 | F6: =1/(1+$J$3)^B6 -> 0.36836417 | G6: =1/(1+$K$3)^B6 -> 0.33434043 | H6: =1/(1+$L$3)^B6 -> 0.30230212 | J6: ='Discount Rate'!$F$6 -> 0.395 | K6: ='Discount Rate'!$G$6 -> 0.4408 | L6: ='Discount Rate'!$H$6 -> 0.49
B7: 4 | C7: =C6*(1.44) -> 2438123.2 | D7: =D6*(1.44) -> 2023642.2 | E7: =E6*1.44 -> 1609161.3 | F7: =1/(1+$J$3)^B7 -> 0.26406033 | G7: =1/(1+$K$3)^B7 -> 0.23205194 | H7: =1/(1+$L$3)^B7 -> 0.20288733 | J7: ='Discount Rate'!$F$6 -> 0.395 | K7: ='Discount Rate'!$G$6 -> 0.4408 | L7: ='Discount Rate'!$H$6 -> 0.49
B8: 5 | C8: =C7*(1.44) -> 3510897.4 | D8: =D7*(1.44) -> 2914044.8 | E8: =E7*1.44 -> 2317192.3 | F8: =1/(1+$J$3)^B8 -> 0.18929056 | G8: =1/(1+$K$3)^B8 -> 0.1610577 | H8: =1/(1+$L$3)^B8 -> 0.13616599 | J8: ='Discount Rate'!$F$6 -> 0.395 | K8: ='Discount Rate'!$G$6 -> 0.4408 | L8: ='Discount Rate'!$H$6 -> 0.49
B9: 6 | C9: =C8*(1.44) -> 5055692.2 | D9: =D8*(1.44) -> 4196224.5 | E9: =E8*1.44 -> 3336756.9 | F9: =1/(1+$J$3)^B9 -> 0.13569216 | G9: =1/(1+$K$3)^B9 -> 0.11178353 | H9: =1/(1+$L$3)^B9 -> 0.091386573 | J9: ='Discount Rate'!$F$6 -> 0.395 | K9: ='Discount Rate'!$G$6 -> 0.4408 | L9: ='Discount Rate'!$H$6 -> 0.49
B10: 7 | C10: =C9*(1.44) -> 7280196.8 | D10: =D9*(1.44) -> 6042563.3 | E10: =E9*1.44 -> 4804929.9 | F10: =1/(1+$J$3)^B10 -> 0.097270365 | G10: =1/(1+$K$3)^B10 -> 0.077584346 | H10: =1/(1+$L$3)^B10 -> 0.06133327 | J10: ='Discount Rate'!$F$6 -> 0.395 | K10: ='Discount Rate'!$G$6 -> 0.4408 | L10: ='Discount Rate'!$H$6 -> 0.49
B11: 8 | C11: =C10*(1.44) -> 10483483 | D11: =D10*(1.44) -> 8701291.2 | E11: =E10*1.44 -> 6919099 | F11: =1/(1+$J$3)^B11 -> 0.06972786 | G11: =1/(1+$K$3)^B11 -> 0.053848102 | H11: =1/(1+$L$3)^B11 -> 0.041163269 | J11: ='Discount Rate'!$F$6 -> 0.395 | K11: ='Discount Rate'!$G$6 -> 0.4408 | L11: ='Discount Rate'!$H$6 -> 0.49
B12: 9 | C12: =C11*(1.44) -> 15096216 | D12: =D11*(1.44) -> 12529859 | E12: =E11*1.44 -> 9963502.6 | F12: =1/(1+$J$3)^B12 -> 0.049984129 | G12: =1/(1+$K$3)^B12 -> 0.037373752 | H12: =1/(1+$L$3)^B12 -> 0.027626355 | J12: ='Discount Rate'!$F$6 -> 0.395 | K12: ='Discount Rate'!$G$6 -> 0.4408 | L12: ='Discount Rate'!$H$6 -> 0.49
B13: 10 | C13: =C12*(1.44) -> 21738551 | D13: =D12*(1.44) -> 18042997 | E13: =E12*1.44 -> 14347444 | F13: =1/(1+$J$3)^B13 -> 0.035830917 | G13: =1/(1+$K$3)^B13 -> 0.025939584 | H13: =1/(1+$L$3)^B13 -> 0.018541178 | J13: ='Discount Rate'!$F$6 -> 0.395 | K13: ='Discount Rate'!$G$6 -> 0.4408 | L13: ='Discount Rate'!$H$6 -> 0.49
C15: Cashflow Scenario | D15: Best | E15: Best | F15: Best | G15: Base | H15: Base | I15: Base | J15: Worst | K15: Worst | L15: Worst
C17: Discount Rate Scenario | D17: Best | E17: Base | F17: Worst | G17: Best | H17: Base | I17: Worst | J17: Best | K17: Base | L17: Worst
C19: Probability (Monte Carlo) | D19: 0.1813 | E19: 0.2972 | F19: 0.1221 | G19: 0.0732 | H19: 0.1245 | I19: 0.0517 | J19: 0.0429 | K19: 0.0766 | L19: 0.0305
C21: NPV | D21: =C3*F3+C4*F4+C5*F5+C6*F6+C7*F7+C8*F8+C9*F9+C10*F10+C11*F11+C12*F12+C13*F13 -> 6437711.8 | E21: =C3*G3+C4*G4+C5*G5+C6*G6+C7*G7+C8*G8+C9*G9+C10*G10+C11*G11+C12*G12+C13*G13 -> 5310473.3 | F21: =C3*H3+C4*H4+C5*H5+C6*H6+C7*H7+C8*H8+C9*H9+C10*H10+C11*H11+C12*H12+C13*H13 -> 4379835.7 | G21: =D3*F3+D4*F4+D5*F5+D6*F6+D7*F7+D8*F8+D9*F9+D10*F10+D11*F11+D12*F12+D13*F13 -> 5285069.9 | H21: =D3*G3+D4*G4+D5*G5+D6*G6+D7*G7+D8*G8+D9*G9+D10*G10+D11*G11+D12*G12+D13*G13 -> 4349462 | I21: =D3*H3+D4*H4+D5*H5+D6*H6+D7*H7+D8*H8+D9*H9+D10*H10+D11*H11+D12*H12+D13*H13 -> 3577032.8 | J21: =E3*F3+E4*F4+E5*F5+E6*F6+E7*F7+E8*F8+E9*F9+E10*F10+E11*F11+E12*F12+E13*F13 -> 4132428.1 | K21: =E3*G3+E4*G4+E5*G5+E6*G6+E7*G7+E8*G8+E9*G9+E10*G10+E11*G11+E12*G12+E13*G13 -> 3388450.7 | L21: =E3*H3+E4*H4+E5*H5+E6*H6+E7*H7+E8*H8+E9*H9+E10*H10+E11*H11+E12*H12+E13*H13 -> 2774229.8
C22: IRR | D22: =IRR(D27:D37) -> 1.7409537 | E22: =IRR(E27:E37) -> 1.6538246 | F22: =IRR(F27:F37) -> 1.5661949 | G22: =IRR(G27:G37) -> 1.4503071 | H22: =IRR(H27:H37) -> 1.372417 | I22: =IRR(I27:I37) -> 1.2940795 | J22: =IRR(J27:J37) -> 1.1593591 | K22: =IRR(K27:K37) -> 1.0907176 | L22: =IRR(L27:L37) -> 1.0216818
C23: ROI | D23: =D21/-$C$3 -> 18.794346 | E23: =E21/-$C$3 -> 15.50347 | F23: =F21/-$C$3 -> 12.786553 | G23: =G21/-$C$3 -> 15.429307 | H23: =H21/-$C$3 -> 12.69788 | I23: =I21/-$C$3 -> 10.442839 | J23: =J21/-$C$3 -> 12.064268 | K23: =K21/-$C$3 -> 9.8922901 | L23: =L21/-$C$3 -> 8.0991253
C24: Payback Period | D24: =-$C$3/$C$4 -> 0.41950405 | E24: =-$C$3/$C$4 -> 0.41950405 | F24: =-$C$3/$C$4 -> 0.41950405 | G24: =-$D$3/$D$4 -> 0.50542656 | H24: =-$D$3/$D$4 -> 0.50542656 | I24: =-$D$3/$D$4 -> 0.50542656 | J24: =-$E$3/$E$4 -> 0.63561219 | K24: =-$E$3/$E$4 -> 0.63561219 | L24: =-$E$3/$E$4 -> 0.63561219
C26: Year | D26: Discounted Cashflows | N26: Expected Cashflow
C27: 0 | D27: =C3*F3 -> -342534.5 | E27: =C3*G3 -> -342534.5 | F27: =C3*H3 -> -342534.5 | G27: =D3*F3 -> -342534.5 | H27: =D3*G3 -> -342534.5 | I27: =D3*H3 -> -342534.5 | J27: =E3*F3 -> -342534.5 | K27: =E3*G3 -> -342534.5 | L27: =E3*H3 -> -342534.5 | N27: =$D$19*D27+$E$19*E27+$F$19*F27+$G$19*G27+$H$19*H27+$I$19*I27+$J$19*J27+$K$19*K27+$L$19*L27 -> -342534.5
C28: 1 | D28: =C4*F4 -> 585320.8 | E28: =C4*G4 -> 566714.69 | F28: =C4*H4 -> 548001.69 | G28: =D4*F4 -> 485816.27 | H28: =D4*G4 -> 470373.19 | I28: =D4*H4 -> 454841.4 | J28: =E4*F4 -> 386311.73 | K28: =E4*G4 -> 374031.69 | L28: =E4*H4 -> 361681.12 | N28: =$D$19*D28+$E$19*E28+$F$19*F28+$G$19*G28+$H$19*H28+$I$19*I28+$J$19*J28+$K$19*K28+$L$19*L28 -> 515350.66
C29: 2 | D29: =C5*F5 -> 604202.12 | E29: =C5*G5 -> 566400.02 | F29: =C5*H5 -> 529612.37 | G29: =D5*F5 -> 501487.76 | H29: =D5*G5 -> 470112.02 | I29: =D5*H5 -> 439578.27 | J29: =E5*F5 -> 398773.4 | K29: =E5*G5 -> 373824.01 | L29: =E5*H5 -> 349544.17 | N29: =$D$19*D29+$E$19*E29+$F$19*F29+$G$19*G29+$H$19*H29+$I$19*I29+$J$19*J29+$K$19*K29+$L$19*L29 -> 516909.04
C30: 3 | D30: =C6*F6 -> 623692.51 | E30: =C6*G6 -> 566085.53 | F30: =C6*H6 -> 511840.15 | G30: =D6*F6 -> 517664.78 | H30: =D6*G6 -> 469850.99 | I30: =D6*H6 -> 424827.32 | J30: =E6*F6 -> 411637.06 | K30: =E6*G6 -> 373616.45 | L30: =E6*H6 -> 337814.5 | N30: =$D$19*D30+$E$19*E30+$F$19*F30+$G$19*G30+$H$19*H30+$I$19*I30+$J$19*J30+$K$19*K30+$L$19*L30 -> 518746.43
C31: 4 | D31: =C7*F7 -> 643811.62 | E31: =C7*G7 -> 565771.21 | F31: =C7*H7 -> 494664.3 | G31: =D7*F7 -> 534363.65 | H31: =D7*G7 -> 469590.1 | I31: =D7*H7 -> 410571.37 | J31: =E7*F7 -> 424915.67 | K31: =E7*G7 -> 373409 | L31: =E7*H7 -> 326478.44 | N31: =$D$19*D31+$E$19*E31+$F$19*F31+$G$19*G31+$H$19*H31+$I$19*I31+$J$19*J31+$K$19*K31+$L$19*L31 -> 520864.29
C32: 5 | D32: =C8*F8 -> 664579.74 | E32: =C8*G8 -> 565457.07 | F32: =C8*H8 -> 478064.83 | G32: =D8*F8 -> 551601.18 | H32: =D8*G8 -> 469329.37 | I32: =D8*H8 -> 396793.81 | J32: =E8*F8 -> 438622.63 | K32: =E8*G8 -> 373201.66 | L32: =E8*H8 -> 315522.79 | N32: =$D$19*D32+$E$19*E32+$F$19*F32+$G$19*G32+$H$19*H32+$I$19*I32+$J$19*J32+$K$19*K32+$L$19*L32 -> 523264.42
C33: 6 | D33: =C9*F9 -> 686017.8 | E33: =C9*G9 -> 565143.1 | F33: =C9*H9 -> 462022.38 | G33: =D9*F9 -> 569394.77 | H33: =D9*G9 -> 469068.77 | I33: =D9*H9 -> 383478.58 | J33: =E9*F9 -> 452771.75 | K33: =E9*G9 -> 372994.45 | L33: =E9*H9 -> 304934.77 | N33: =$D$19*D33+$E$19*E33+$F$19*F33+$G$19*G33+$H$19*H33+$I$19*I33+$J$19*J33+$K$19*K33+$L$19*L33 -> 525948.88
C34: 7 | D34: =C10*F10 -> 708147.4 | E34: =C10*G10 -> 564829.31 | F34: =C10*H10 -> 446518.28 | G34: =D10*F10 -> 587762.34 | H34: =D10*G10 -> 468808.32 | I34: =D10*H10 -> 370610.17 | J34: =E10*F10 -> 467377.29 | K34: =E10*G10 -> 372787.34 | L34: =E10*H10 -> 294702.06 | N34: =$D$19*D34+$E$19*E34+$F$19*F34+$G$19*G34+$H$19*H34+$I$19*I34+$J$19*J34+$K$19*K34+$L$19*L34 -> 528920.07
C35: 8 | D35: =C11*F11 -> 730990.87 | E35: =C11*G11 -> 564515.69 | F35: =C11*H11 -> 431534.44 | G35: =D11*F11 -> 606722.42 | H35: =D11*G11 -> 468548.02 | I35: =D11*H11 -> 358173.59 | J35: =E11*F11 -> 482453.97 | K35: =E11*G11 -> 372580.35 | L35: =E11*H11 -> 284812.73 | N35: =$D$19*D35+$E$19*E35+$F$19*F35+$G$19*G35+$H$19*H35+$I$19*I35+$J$19*J35+$K$19*K35+$L$19*L35 -> 532180.66
C36: 9 | D36: =C12*F12 -> 754571.22 | E36: =C12*G12 -> 564202.24 | F36: =C12*H12 -> 417053.42 | G36: =D12*F12 -> 626294.11 | H36: =D12*G12 -> 468287.86 | I36: =D12*H12 -> 346154.34 | J36: =E12*F12 -> 498017 | K36: =E12*G12 -> 372373.48 | L36: =E12*H12 -> 275255.26 | N36: =$D$19*D36+$E$19*E36+$F$19*F36+$G$19*G36+$H$19*H36+$I$19*I36+$J$19*J36+$K$19*K36+$L$19*L36 -> 535733.66
C37: 10 | D37: =C13*F13 -> 778912.22 | E37: =C13*G13 -> 563888.97 | F37: =C13*H13 -> 403058.34 | G37: =D13*F13 -> 646497.15 | H37: =D13*G13 -> 468027.84 | I37: =D13*H13 -> 334538.42 | J37: =E13*F13 -> 514082.07 | K37: =E13*G13 -> 372166.72 | L37: =E13*H13 -> 266018.5 | N37: =$D$19*D37+$E$19*E37+$F$19*F37+$G$19*G37+$H$19*H37+$I$19*I37+$J$19*J37+$K$19*K37+$L$19*L37 -> 539582.36
C39: Expected NPV | D39: =D19*D21+E19*E21+F19*F21+G19*G21+H19*H21+I19*I21+J19*J21+K19*K21+L19*L21 -> 4914966
C40: Expected IRR | D40: =IRR(N27:N37) -> 1.5077368
C41: Expected ROI | D41: =D19*D23+E19*E23+F19*F23+G19*G23+H19*H23+I19*I23+J19*J23+K19*K23+L19*L23 -> 14.34882
C42: Expected Payback Period | D42: =D19*D24+E19*E24+F19*F24+G19*G24+H19*H24+I19*I24+J19*J24+K19*K24+L19*L24 -> 0.47334934

Sheet Discount Rate
B2: Component | C2: Current Rate | E2: Explanation | F2: Best Scenario | G2: Base Scenario | H2: Worst Scenario
B3: Risk-free Rate | C3: 0.2869 | E3: Turkey 10-Year Government Bond Rate (28.69%) | F3: 0.25 | G3: 0.2869 | H3: 0.32
B4: Country Risk Premium | C4: 0.0339 | E4: Turkey's CDS Premium (3.39%) | F4: 0.025 | G4: 0.0339 | H4: 0.05
B5: Project Spesific Risk Premium | C5: 0.12 | E5: Project Specific Risk Premium (12%) | F5: 0.12 | G5: 0.12 | H5: 0.12
B6: Discount Rate | C6: =SUM(C3:C5) -> 0.4408 | E6: Total Discount Rate (44.08) | F6: =SUM(F3:F5) -> 0.395 | G6: =SUM(G3:G5) -> 0.4408 | H6: =SUM(H3:H5) -> 0.49

Sheet Capacity Using Rate & Cash Flow
C2: Capacity Using Rate (Best) (100%) | D2: Capacity Using Rate (Base) (83%) | E2: Capacity Using Rate (Worst) (66%) | G2: 1 | H2: 0.83 | I2: 0.66
B3: Seasonal Revenue | C3: 1335000 | D3: =C3*H2 -> 1108050 | E3: =C3*I2 -> 881100
B4: Investment Amount | C4: 342534.5 | D4: =C4 -> 342534.5 | E4: =C4 -> 342534.5
B5: Seasonal Expense | C5: 518477.48 | D5: =C5*H2 -> 430336.31 | E5: =C5*I2 -> 342195.14
B7: Cash Flow (Year 0) | C7: =-C4 -> -342534.5 | D7: =-D4 -> -342534.5 | E7: =-E4 -> -342534.5
B8: Cash Flow (Year 1) | C8: =($C$3-$C$5) -> 816522.52 | D8: =($D$3-$D$5) -> 677713.69 | E8: =($E$3-$E$5) -> 538904.86
B9: Cash Flow (Year 2) | C9: =($C$3-$C$5) -> 816522.52 | D9: =($D$3-$D$5) -> 677713.69 | E9: =($E$3-$E$5) -> 538904.86
B10: Cash Flow (Year 3) | C10: =($C$3-$C$5) -> 816522.52 | D10: =($D$3-$D$5) -> 677713.69 | E10: =($E$3-$E$5) -> 538904.86
B11: Cash Flow (Year 4) | C11: =($C$3-$C$5) -> 816522.52 | D11: =($D$3-$D$5) -> 677713.69 | E11: =($E$3-$E$5) -> 538904.86
B12: Cash Flow (Year 5) | C12: =($C$3-$C$5) -> 816522.52 | D12: =($D$3-$D$5) -> 677713.69 | E12: =($E$3-$E$5) -> 538904.86
B13: Cash Flow (Year 6) | C13: =($C$3-$C$5) -> 816522.52 | D13: =($D$3-$D$5) -> 677713.69 | E13: =($E$3-$E$5) -> 538904.86
B14: Cash Flow (Year 7) | C14: =($C$3-$C$5) -> 816522.52 | D14: =($D$3-$D$5) -> 677713.69 | E14: =($E$3-$E$5) -> 538904.86
B15: Cash Flow (Year 8) | C15: =($C$3-$C$5) -> 816522.52 | D15: =($D$3-$D$5) -> 677713.69 | E15: =($E$3-$E$5) -> 538904.86
B16: Cash Flow (Year 9) | C16: =($C$3-$C$5) -> 816522.52 | D16: =($D$3-$D$5) -> 677713.69 | E16: =($E$3-$E$5) -> 538904.86
B17: Cash Flow (Year 10) | C17: =($C$3-$C$5) -> 816522.52 | D17: =($D$3-$D$5) -> 677713.69 | E17: =($E$3-$E$5) -> 538904.86

Sheet Monte Carlo Simülasyonu
B2: Faiz Senaryosu | C2: Faiz Olasılık | D2: Satış Senaryosu | E2: Satış Olasılık | F2: NPV Değeri | H2: Simülasyon No | I2: Rastgele Faiz | J2: Rastgele Satış | L2: Monte Carlo Simulation | M2: NPV | N2: Number of Selection | O2: Probability (%)
B3: Yüksek | C3: 0.2 | D3: Yüksek | E3: 60 | F3: 6437711.8 | H3: 1 | I3: =RANDBETWEEN(0,1) -> 0 | J3: =RANDBETWEEN(0,1) -> 1 | M3: 2774229.8 | N3: 305 | O3: 3.05
B4: Yüksek | C4: 0.2 | D4: Orta | E4: 25 | F4: 5285069.9 | H4: 2 | I4: =RANDBETWEEN(0,1) -> 1 | J4: =RANDBETWEEN(0,1) -> 0 | M4: 3388450.7 | N4: 766 | O4: 7.66
B5: Yüksek | C5: 0.2 | D5: Düşük | E5: 15 | F5: 4132428.1 | H5: 3 | I5: =RANDBETWEEN(0,1) -> 0 | J5: =RANDBETWEEN(0,1) -> 0 | M5: 3577032.8 | N5: 517 | O5: 5.17
B6: Orta | C6: 0.5 | D6: Yüksek | E6: 60 | F6: 5310473.3 | H6: 4 | I6: =RANDBETWEEN(0,1) -> 1 | J6: =RANDBETWEEN(0,1) -> 0 | M6: 4132428.1 | N6: 429 | O6: 4.29
B7: Orta | C7: 0.5 | D7: Orta | E7: 25 | F7: 4349462 | H7: 5 | I7: =RANDBETWEEN(0,1) -> 0 | J7: =RANDBETWEEN(0,1) -> 0 | M7: 4349462 | N7: 1245 | O7: 12.45
B8: Orta | C8: 0.5 | D8: Düşük | E8: 15 | F8: 3388450.7 | H8: 6 | I8: =RANDBETWEEN(0,1) -> 0 | J8: =RANDBETWEEN(0,1) -> 1 | M8: 4379835.7 | N8: 1221 | O8: 12.21
B9: Düşük | C9: 0.3 | D9: Yüksek | E9: 60 | F9: 4379835.7 | H9: 7 | I9: =RANDBETWEEN(0,1) -> 1 | J9: =RANDBETWEEN(0,1) -> 0 | M9: 5285069.9 | N9: 732 | O9: 7.32
B10: Düşük | C10: 0.3 | D10: Orta | E10: 25 | F10: 3577032.8 | H10: 8 | I10: =RANDBETWEEN(0,1) -> 0 | J10: =RANDBETWEEN(0,1) -> 0 | M10: 5310473.3 | N10: 2972 | O10: 29.72
B11: Düşük | C11: 0.3 | D11: Düşük | E11: 15 | F11: 2774229.8 | H11: 9 | I11: =RANDBETWEEN(0,1) -> 0 | J11: =RANDBETWEEN(0,1) -> 1 | M11: 6437711.8 | N11: 1813 | O11: 18.13
H12: 10 | I12: =RANDBETWEEN(0,1) -> 0 | J12: =RANDBETWEEN(0,1) -> 0
H13: 11 | I13: =RANDBETWEEN(0,1) -> 1 | J13: =RANDBETWEEN(0,1) -> 0
H14: 12 | I14: =RANDBETWEEN(0,1) -> 0 | J14: =RANDBETWEEN(0,1) -> 1
H15: 13 | I15: =RANDBETWEEN(0,1) -> 0 | J15: =RANDBETWEEN(0,1) -> 0
H16: 14 | I16: =RANDBETWEEN(0,1) -> 1 | J16: =RANDBETWEEN(0,1) -> 0
H17: 15 | I17: =RANDBETWEEN(0,1) -> 0 | J17: =RANDBETWEEN(0,1) -> 1
H18: 16 | I18: =RANDBETWEEN(0,1) -> 0 | J18: =RANDBETWEEN(0,1) -> 1
H19: 17 | I19: =RANDBETWEEN(0,1) -> 0 | J19: =RANDBETWEEN(0,1) -> 0
H20: 18 | I20: =RANDBETWEEN(0,1) -> 0 | J20: =RANDBETWEEN(0,1) -> 1
H21: 19 | I21: =RANDBETWEEN(0,1) -> 0 | J21: =RANDBETWEEN(0,1) -> 1
H22: 20 | I22: =RANDBETWEEN(0,1) -> 1 | J22: =RANDBETWEEN(0,1) -> 1
H23: 21 | I23: =RANDBETWEEN(0,1) -> 0 | J23: =RANDBETWEEN(0,1) -> 0
... H1002: 1000 | I1002: =RANDBETWEEN(0,1) -> 1 | J1002: =RANDBETWEEN(0,1) -> 0

Sheet Index Scoring Model
B2: Index Scoring Model | C2: ID | D2: Factor | E2: Coefficient | F2: Score | G2: Weighted Score
C3: 1 | D3: Willingness to Rent | E3: 0.3 | F3: 0.915 | G3: =E3*F3 -> 0.2745
C4: 2 | D4: Competition | E4: 0.2 | F4: 1 | G4: =E4*F4 -> 0.2
C5: 3 | D5: Economy | E5: 0.1 | F5: 0.7 | G5: =E5*F5 -> 0.07
C6: 5 | D6: Affordability | E6: 0.1 | F6: 0.6 | G6: =E6*F6 -> 0.06
C7: 6 | D7: Attractiveness | E7: 0.1 | F7: 0.9 | G7: =E7*F7 -> 0.09
C8: 4 | D8: Marketing | E8: 0.05 | F8: 0.6 | G8: =E8*F8 -> 0.03
C9: 7 | D9: Accessibility | E9: 0.05 | F9: 0.7 | G9: =E9*F9 -> 0.035
C10: 9 | D10: Alternative Use | E10: 0.05 | F10: 0.7 | G10: =E10*F10 -> 0.035
C11: 10 | D11: Environmental Sensitivity | E11: 0.05 | F11: 0.8 | G11: =E11*F11 -> 0.04
C12: Base Scenario | G12: =SUM(G3:G11) -> 0.8345

Sheet Seasonal Price Estimation
B2: Seasonal Vegetable Price Forecasts
B3: Product | C3: Demand Coefficient | D3: 2024 Wholesale Prices | E3: Food Inflation Expectations | F3: Expected 2025 Prices | G3: Weighted Basket Share
B4: Tomato | C4: 0.3 | D4: 20 | E4: 0.5891 | F4: =D4*(1+E4) -> 31.782 | G4: =F4*C4 -> 9.5346
B5: Cucumber | C5: 0.15 | D5: 20 | E5: 0.5891 | F5: =D5*(1+E5) -> 31.782 | G5: =F5*C5 -> 4.7673
B6: Pepper | C6: 0.15 | D6: 55 | E6: 0.5891 | F6: =D6*(1+E6) -> 87.4005 | G6: =F6*C6 -> 13.110075
B7: Eggplant | C7: 0.1 | D7: 40 | E7: 0.5891 | F7: =D7*(1+E7) -> 63.564 | G7: =F7*C7 -> 6.3564
B8: Bean | C8: 0.1 | D8: 100 | E8: 0.5891 | F8: =D8*(1+E8) -> 158.91 | G8: =F8*C8 -> 15.891
B9: Zucchini | C9: 0.05 | D9: 30 | E9: 0.5891 | F9: =D9*(1+E9) -> 47.673 | G9: =F9*C9 -> 2.38365
B10: Stuffed Pepper | C10: 0.05 | D10: 60 | E10: 0.5891 | F10: =D10*(1+E10) -> 95.346 | G10: =F10*C10 -> 4.7673
B11: Gherkin | C11: 0.05 | D11: 7 | E11: 0.5891 | F11: =D11*(1+E11) -> 11.1237 | G11: =F11*C11 -> 0.556185
B12: Okra | C12: 0.05 | D12: 110 | E12: 0.5891 | F12: =D12*(1+E12) -> 174.801 | G12: =F12*C12 -> 8.74005
B13: BASKET | C13: =SUM(C4:C12) -> 1 | D13: =SUMPRODUCT(C4:C12,D4:D12) -> 41.6 | E13: 0.7 | F13: =AVERAGE(F4:F12) -> 78.042467 | G13: =SUM(G4:G12) -> 66.10656
B15: The Total Price the Consumer would Normally Pay for Products (TOTAL 270 KG): | G15: =(21705/80)*F13 -> 21173.897
B17: Our Price | G17: 17500 TL + VAT
